mp3/__init__.py
youtube_mp3_downloader-1.4.data/scripts/mp3
youtube_mp3_downloader-1.4.dist-info/DESCRIPTION.rst
youtube_mp3_downloader-1.4.dist-info/METADATA
youtube_mp3_downloader-1.4.dist-info/RECORD
youtube_mp3_downloader-1.4.dist-info/WHEEL
youtube_mp3_downloader-1.4.dist-info/metadata.json
youtube_mp3_downloader-1.4.dist-info/top_level.txt
